{
  "products": [
    {
      "id": 1,
      "name": "T-Shirt",
      "price": 10,
      "description": "A simple T-Shirt",
      "image": "https://unblast.com/wp-content/uploads/2018/09/T-shirt-Mockup.jpg",
      "attributes": [
        {
          "name": "fabric",
          "options": [
            "cotton",
            "polyester",
            "wool",
            "rayon",
            "linen"
          ]
        },
        {
          "name": "size",
          "options": [
            "small",
            "medium",
            "large"
          ]
        },
        {
          "name": "color",
          "options": [
            "red",
            "blue",
            "green",
            "yellow",
            "white",
            "black"
          ]
        },
        {
          "name": "style",
          "options": [
            "v-neck",
            "crew-neck"
          ]
        },
        {
          "name": "placement",
          "options": []
        },
        {
          "name": "purpose",
          "options": [
            "business",
            "personal",
            "gift"
          ]
        },
        {
          "name": "description",
          "options": [
            "I want a picture of a cat on the front",
            "I want a picture of a dog on the back"
          ]
        }
      ]
    },
    {
      "id": 2,
      "name": "Banner",
      "price": 10,
      "description": "A simple Banner",
      "image": "https://unblast.com/wp-content/uploads/2018/10/Rollup-Mockup.jpg",
      "attributes": [
        {
          "name": "material",
          "options": [
            "vinyl",
            "fabric",
            "mesh"
          ]
        },
        {
          "name": "dimensions",
          "options": []
        },
        {
          "name": "unit",
          "options": [
            "ft",
            "in",
            "cm",
            "m"
          ]
        },
        {
          "name": "purpose",
          "options": [
            "business",
            "personal",
            "gift"
          ]
        },
        {
          "name": "description",
          "options": [
            "I want a picture of a cat on the front",
            "I want a picture of a dog on the back"
          ]
        },
        {
          "name": "side",
          "options": [
            "single",
            "double"
          ]
        }
      ]
    },
    {
      "id": 3,
      "name": "Sticker",
      "price": 10,
      "description": "A simple Sticker",
      "image": "https://unblast.com/wp-content/uploads/2020/10/Red-Grey-Watercolor-Floral-Clipart-1.jpg",
      "attributes": [
        {
          "name": "material",
          "options": [
            "vinyl",
            "fabric",
            "mesh"
          ]
        },
        {
          "name": "unit",
          "options": [
            "ft",
            "in",
            "cm",
            "m"
          ]
        },
        {
          "name": "purpose",
          "options": [
            "business",
            "personal",
            "gift"
          ]
        },
        {
          "name": "description",
          "options": [
            "I want a picture of a cat on the front",
            "I want a picture of a dog on the back"
          ]
        },
        {
          "name": "side",
          "options": [
            "single",
            "double"
          ]
        }
      ]
    }
  ],
  "orders": [
    {
      "id": "366b",
      "series": "SAL-ORD-YYYY-",
      "date": "Mar 11, 2024",
      "deliveryDate": "Mar 13, 2024",
      "orderType": "telegram",
      "description": "Uv and Baneer sticker",
      "customerPhone": "0905-07-8826",
      "customerFirstName": "CocaCola",
      "customerEmail": "cocacola@gmail.com",
      "commissionPhone": "0905-08-8266",
      "commissionFirstName": "Muhammed",
      "commissionEmail": "admin@domino.com",
      "customerId": "1710128272183",
      "commissionId": "1710111531529",
      "commissionType": "commission",
      "orderItems": [
        {
          "machine": "UV",
          "material": "Film",
          "service": "Print and Material",
          "unitPrice": 8000,
          "status": "recieved"
        },
        {
          "machine": "BANNER",
          "material": "sticker",
          "service": "Print",
          "unitPrice": 16000,
          "status": "recieved"
        }
      ],
      "orderMeasures": [
        {
          "unitName": null,
          "width": "5",
          "height": "2",
          "quantity": "4",
          "unitPrice": null
        },
        {
          "unitName": null,
          "width": "5",
          "height": "4",
          "quantity": "4",
          "unitPrice": null
        }
      ],
      "totalBirr": 24000,
      "grandTotal": 27600,
      "fileNames": [
        "CocaCola-UV-Film-5x2",
        "CocaCola-BANNER-sticker-5x4"
      ],
      "totalQuantity": 8,
      "paymentInfo": {
        "paymentMethod": "cash",
        "paymentReference": "",
        "paymentAmount": 0,
        "paymentStatus": "not paid"
      }
    }
  ],
  "customers": [
    {
      "id": 1707080341356,
      "phone": "0905-07-8826",
      "companyType": "individual",
      "firstName": "Muhammed",
      "lastName": "Berisso",
      "email": "muhammedb8826@gmail.com"
    },
    {
      "id": "1707080747266",
      "phone": "0911-04-0506",
      "companyType": "group",
      "firstName": "Berisso",
      "lastName": "Family",
      "email": "berisso@gmail.com"
    },
    {
      "id": "1707080869403",
      "phone": "0916-01-6212",
      "companyType": "company",
      "firstName": "Kuma",
      "lastName": "Shark",
      "email": "kuma@gmail.com"
    },
    {
      "id": "1707089336029",
      "phone": "0911-88-9696",
      "companyType": "",
      "firstName": "Teshe",
      "lastName": "",
      "email": ""
    },
    {
      "id": "1707089362257",
      "phone": "0988-45-6666",
      "companyType": "",
      "firstName": "Babi",
      "lastName": "",
      "email": ""
    },
    {
      "id": "1707089382443",
      "phone": "0926-98-0318",
      "companyType": "",
      "firstName": "Osman",
      "lastName": "",
      "email": ""
    },
    {
      "id": "1707089490260",
      "phone": "0911-07-0000",
      "companyType": "",
      "firstName": "Basha",
      "lastName": "",
      "email": ""
    },
    {
      "id": "1707594176543",
      "phone": "1234-56-7890",
      "companyType": "individual",
      "firstName": "Teshager",
      "lastName": "Assefa",
      "email": "teshagerass@gmail.com"
    },
    {
      "id": "1707595667165",
      "phone": "1234-56-7896",
      "companyType": "company",
      "firstName": "Mamila",
      "lastName": "",
      "email": "mamila@gmail.com"
    },
    {
      "id": "1707603896773",
      "phone": "0916-11-5252",
      "companyType": "individual",
      "firstName": "Muktar",
      "lastName": "",
      "email": "muktar@gmail.com"
    },
    {
      "id": "1707706533313",
      "phone": "0910-11-1111",
      "companyType": "company",
      "firstName": "Duche",
      "lastName": "",
      "email": "duche@gmail.com"
    },
    {
      "id": "1707746857768",
      "phone": "1234-56-7890",
      "companyType": "individual",
      "firstName": "ahadu",
      "lastName": "teshager",
      "email": "admin@domino.com"
    },
    {
      "id": "1707883674950",
      "phone": "9856-59-8000",
      "companyType": "individual",
      "firstName": "test",
      "lastName": "test",
      "email": "admin@domino.com"
    },
    {
      "id": "1710128272183",
      "phone": "0905-07-8826",
      "companyType": "company",
      "firstName": "CocaCola",
      "lastName": "",
      "email": "cocacola@gmail.com"
    }
  ],
  "services": [
    {
      "id": "e4b1",
      "name": "Print and Material"
    },
    {
      "id": "1324",
      "name": "Print and Heat press"
    },
    {
      "id": "b664",
      "name": "Print"
    }
  ],
  "machines": [
    {
      "id": "54dd",
      "name": "DTFFF"
    },
    {
      "id": "f084",
      "name": "BANNER"
    },
    {
      "id": "5b90",
      "name": "vvvv"
    }
  ],
  "materials": [
    {
      "id": "9944",
      "name": "T-shirt"
    },
    {
      "id": "e4b1",
      "name": "Film"
    },
    {
      "id": "1f8f",
      "name": "Screen"
    },
    {
      "id": "5609",
      "name": "sticker"
    }
  ],
  "units": [
    {
      "id": "90fc",
      "name": "M",
      "width": "10",
      "height": "10"
    },
    {
      "id": "1bd6",
      "name": "Linear",
      "width": "0.6",
      "height": "1"
    },
    {
      "id": "8dd4",
      "name": "PCS",
      "width": "1",
      "height": "1"
    },
    {
      "id": "890e",
      "name": "sqm",
      "width": "1",
      "height": "1"
    }
  ],
  "prices": [
    {
      "id": "d841",
      "machine": {
        "id": "54dd",
        "name": "DTF"
      },
      "material": {
        "id": "9944",
        "name": "T-shirt"
      },
      "service": {
        "id": "e4b1",
        "name": "Print and Material"
      },
      "unit": {
        "id": "8dd4",
        "name": "PCS",
        "width": "1",
        "height": "1"
      },
      "unitPrice": "100"
    },
    {
      "id": "32cb",
      "machine": {
        "id": "8b9a",
        "name": "UV"
      },
      "material": {
        "id": "e4b1",
        "name": "Film"
      },
      "service": {
        "id": "e4b1",
        "name": "Print and Material"
      },
      "unit": {
        "id": "90fc",
        "name": "M",
        "width": "10",
        "height": "10"
      },
      "unitPrice": "200"
    },
    {
      "id": "624d",
      "machine": {
        "id": "f084",
        "name": "BANNER"
      },
      "material": {
        "id": "1f8f",
        "name": "Screen"
      },
      "service": {
        "id": "e4b1",
        "name": "Print and Material"
      },
      "unit": {
        "id": "90fc",
        "name": "M",
        "width": "10",
        "height": "10"
      },
      "unitPrice": "50"
    },
    {
      "id": "ec50",
      "machine": {
        "id": "54dd",
        "name": "DTF"
      },
      "material": {
        "id": "9944",
        "name": "T-shirt"
      },
      "service": {
        "id": "1324",
        "name": "Print and Heat press"
      },
      "unit": {
        "id": "8dd4",
        "name": "PCS",
        "width": "1",
        "height": "1"
      },
      "unitPrice": "200"
    },
    {
      "id": "9c22",
      "machine": {
        "id": "f084",
        "name": "BANNER"
      },
      "material": {
        "id": "1f8f",
        "name": "Screen"
      },
      "service": {
        "id": "b664",
        "name": "Print"
      },
      "unit": {
        "id": "90fc",
        "name": "M",
        "width": "10",
        "height": "10"
      },
      "unitPrice": "300"
    },
    {
      "id": "ceb6",
      "machine": {
        "id": "f084",
        "name": "BANNER"
      },
      "material": {
        "id": "1f8f",
        "name": "Screen"
      },
      "service": {
        "id": "1324",
        "name": "Print and Heat press"
      },
      "unit": {
        "id": "90fc",
        "name": "M",
        "width": "10",
        "height": "10"
      },
      "unitPrice": "400"
    },
    {
      "id": "955d",
      "machine": {
        "id": "f084",
        "name": "BANNER"
      },
      "material": {
        "id": "5609",
        "name": "sticker"
      },
      "service": {
        "id": "b664",
        "name": "Print"
      },
      "unit": {
        "id": "890e",
        "name": "sqm",
        "width": "1",
        "height": "1"
      },
      "unitPrice": "200"
    }
  ],
  "roles": [
    {
      "id": "5932",
      "name": " Reception",
      "description": "She can create an order"
    }
  ],
  "permissions": [
    {
      "id": 1,
      "name": "create",
      "description": "Can create items"
    },
    {
      "id": 2,
      "name": "read",
      "description": "Can read items"
    },
    {
      "id": 3,
      "name": "update",
      "description": "Can update items"
    },
    {
      "id": 4,
      "name": "delete",
      "description": "Can delete items"
    }
  ],
  "dicounts": [
    {
      "id": "2b12",
      "level": "1",
      "minumumMeterSquare": "100",
      "discountPercentage": "15"
    },
    {
      "id": "a09d",
      "level": "2",
      "minumumMeterSquare": "150",
      "discountPercentage": "20"
    },
    {
      "id": "a88c",
      "level": "3",
      "minumumMeterSquare": "500",
      "discountPercentage": "30"
    },
    {
      "id": "b8b8",
      "level": "4",
      "minumumMeterSquare": "1000",
      "discountPercentage": "50"
    }
  ],
  "commissions": [
    {
      "id": "1710111531529",
      "phone": "0905-08-8266",
      "companyType": "individual",
      "firstName": "Muhammed",
      "lastName": "",
      "email": "admin@domino.com"
    },
    {
      "id": "1710126934041",
      "phone": "1234-56-7890",
      "companyType": "company",
      "firstName": "Teshager",
      "lastName": "Assefa",
      "email": "teshagerass@gmail.com"
    },
    {
      "id": "1710127040750",
      "phone": "1234-56-7890",
      "companyType": "individual",
      "firstName": "Muktar",
      "lastName": "Berisso",
      "email": "muktar@gmail.com"
    }
  ]
}